ChangeCoordinate_zl/ChangeCoordinate_zl.py
ChangeCoordinate_zl/__init__.py
ChangeCoordinate_zl-2.0.dist-info/METADATA
ChangeCoordinate_zl-2.0.dist-info/WHEEL
ChangeCoordinate_zl-2.0.dist-info/top_level.txt
ChangeCoordinate_zl-2.0.dist-info/RECORD
